wz_core_points_utils/__about__.py
wz_core_points_utils/__init__.py
wz_core_points_utils/_polygon_to_grid.py
wz_core_points_utils/diamond14.py
wz_core_points_utils-0.0.2.dist-info/METADATA
wz_core_points_utils-0.0.2.dist-info/WHEEL
wz_core_points_utils-0.0.2.dist-info/licenses/LICENSE.txt
wz_core_points_utils-0.0.2.dist-info/RECORD
