Metadata-Version: 2.3
Name: wz-core-points-utils
Version: 0.0.2
Project-URL: Documentation, https://github.com/yjw/wz-core-points-utils#readme
Project-URL: Issues, https://github.com/yjw/wz-core-points-utils/issues
Project-URL: Source, https://github.com/yjw/wz-core-points-utils
Author-email: yjw <1633998687@qq.com>
License-Expression: MIT
License-File: LICENSE.txt
Classifier: Development Status :: 4 - Beta
Classifier: Programming Language :: Python :: 3.8
Classifier: Programming Language :: Python :: 3.9
Classifier: Programming Language :: Python :: 3.10
Classifier: Programming Language :: Python :: 3.11
Classifier: Programming Language :: Python :: 3.12
Requires-Python: >=3.8
